[
  {"front": "die Energie (Sg)", "back": "energy"},
  {"front": "wechseln (haben)", "back": "to change / to switch"},
  {"front": "die Decke, -n", "back": "ceiling / blanket"},
  {"front": "hängen (haben)", "back": "to hang"},
  {"front": "oben (Adv)", "back": "above / upstairs"},
  {"front": "der Dank (Sg)", "back": "thanks / gratitude"},
  {"front": "die Menge, -n", "back": "quantity / crowd"},
  {"front": "die Kassette, -n", "back": "cassette / tape"},
  {"front": "der Kugelschreiber, -", "back": "ballpoint pen"},
  {"front": "stecken (haben)", "back": "to stick / to put in"},
  {"front": "das Schloss, die Schlösser", "back": "lock / castle"},
  {"front": "das Bild, -er", "back": "picture / painting"},
  {"front": "die Wand, die Wände", "back": "wall"},
  {"front": "legen (haben)", "back": "to lay / to put down"},
  {"front": "die Ruhe (Sg)", "back": "quiet / peace"},
  {"front": "das Schild, -er", "back": "sign / plaque"},
  {"front": "wieder (Adv)", "back": "again"},
  {"front": "bauen (haben)", "back": "to build"},
  {"front": "dahin (Adv)", "back": "to there / towards there"},
  {"front": "da (Adv)", "back": "there"},
  {"front": "die Pflanze, -n", "back": "plant"},
  {"front": "dorthin (Adv)", "back": "to there"},
  {"front": "die Vorsicht (Sg)", "back": "caution"},
  {"front": "herunter, runter (Adv)", "back": "down"},
  {"front": "fallen (sein)", "back": "to fall"},
  {"front": "rein (Adv)", "back": "inside / in"},
  {"front": "der Müll (Sg)", "back": "rubbish / trash"},
  {"front": "raus (Adv)", "back": "out / outside"},
  {"front": "reinkommen (sein)", "back": "to come in"},
  {"front": "der Briefkasten, die Briefkästen", "back": "letterbox / mailbox"},
  {"front": "gießen (haben)", "back": "to pour / to water"},
  {"front": "die Katze, -n", "back": "cat"},
  {"front": "werfen (haben)", "back": "to throw"},
  {"front": "das Päckchen, -", "back": "small parcel / package"},
  {"front": "annehmen (haben)", "back": "to accept / to receive"},
  {"front": "das Paket, -e", "back": "parcel / package"},
  {"front": "die Schicht, -en", "back": "layer / shift"},
  {"front": "wirklich (Adj/Adv)", "back": "really / true"},
  {"front": "füttern (haben)", "back": "to feed (animals)"},
  {"front": "klingeln (haben)", "back": "to ring / to chime"},
  {"front": "erwarten (haben)", "back": "to expect"},
  {"front": "der Handwerker, -/", "back": "craftsman / tradesman (male)"},
  {"front": "die Handwerkerin, -nen", "back": "craftswoman / tradeswoman"},
  {"front": "lassen (haben)", "back": "to let / to allow"},
  {"front": "das Plastik (Sg)", "back": "plastic"},
  {"front": "verpacken (haben)", "back": "to wrap / to pack"},
  {"front": "vermeiden (haben)", "back": "to avoid"},
  {"front": "der Moderator, -en", "back": "presenter / host (male)"},
  {"front": "die Moderatorin, -nen", "back": "presenter / host (female)"},
  {"front": "die Aktion, -en", "back": "action / campaign"},
  {"front": "der Deutsche, die Deutschen", "back": "German (male)"},
  {"front": "trennen (haben)", "back": "to separate / to divide"},
  {"front": "bio(logisch) (Adj)", "back": "organic / biological"},
  {"front": "das Experiment, -e", "back": "experiment"},
  {"front": "aufhören (haben)", "back": "to stop / to finish"},
  {"front": "negativ (Adj)", "back": "negative"},
  {"front": "positiv (Adj)", "back": "positive"},
  {"front": "nötig (Adj)", "back": "necessary"},
  {"front": "die Leitung, -en", "back": "line / management / lead"},
  {"front": "recht haben", "back": "to be right"},
  {"front": "das Land (Sg)", "back": "country / land"},
  {"front": "realistisch (Adj)", "back": "realistic"},
  {"front": "die Lösung, -en", "back": "solution / answer"},
  {"front": "verzichten auf (haben)", "back": "to do without / to forego"},
  {"front": "die Umwelt (Sg)", "back": "environment"},
  {"front": "sicher (Adj/Adv)", "back": "safe / certain"},
  {"front": "die (Müll-) Tonne, -n", "back": "bin / rubbish bin"},
  {"front": "die Notiz, -en", "back": "note / memo"},
  {"front": "das Waschmittel, -leer", "back": "washing detergent"},
  {"front": "der Zettel, -", "back": "note / slip of paper"},
  {"front": "das Spielzeug (Sg)", "back": "toy"},
  {"front": "das Kostüm, -e", "back": "costume / suit"},
  {"front": "der Bewohner, -/", "back": "resident / occupant (male)"},
  {"front": "die Bewohnerin, -nen", "back": "resident / occupant (female)"},
  {"front": "müll trennen", "back": "to separate rubbish"},
  {"front": "der Papiermüll (Sg)", "back": "paper waste"},
  {"front": "der Biomüll (Sg)", "back": "biodegradable waste"},
  {"front": "der Abfall, die Abfälle", "back": "waste / rubbish"}
]
